apiperu/__init__.py
apiperu/departamentos.py
apiperu-0.0.3.dist-info/LICENSE
apiperu-0.0.3.dist-info/METADATA
apiperu-0.0.3.dist-info/WHEEL
apiperu-0.0.3.dist-info/top_level.txt
apiperu-0.0.3.dist-info/RECORD
