Metadata-Version: 2.1
Name: apiperu
Version: 0.0.3
Summary: API de los 24 departamentos del Perú
Home-page: https://github.com/brianinhu/apiperu
License-File: LICENSE
Requires-Dist: unidecode
